[  {    "type": "get",    "url": "/cities/CN/cities.json",    "title": "Cities list",    "group": "Locations",    "success": {      "fields": {        "200": [          {            "group": "200",            "type": "object[]",            "optional": false,            "field": "void",            "description": "<p>Cities list</p>"          }        ]      }    },    "version": "0.0.0",    "filename": "routes/index.js",    "groupTitle": "Locations",    "name": "GetCitiesCnCitiesJson"  },  {    "type": "get",    "url": "/cities/CN/provinces.json",    "title": "Provinces list",    "group": "Locations",    "success": {      "fields": {        "200": [          {            "group": "200",            "type": "object[]",            "optional": false,            "field": "void",            "description": "<p>Provinces list</p>"          }        ]      }    },    "version": "0.0.0",    "filename": "routes/index.js",    "groupTitle": "Locations",    "name": "GetCitiesCnProvincesJson"  },  {    "type": "get",    "url": "/countries.json",    "title": "Countries list",    "group": "Locations",    "success": {      "fields": {        "200": [          {            "group": "200",            "type": "object[]",            "optional": false,            "field": "void",            "description": "<p>Countries list</p>"          }        ]      }    },    "version": "0.0.0",    "filename": "routes/index.js",    "groupTitle": "Locations",    "name": "GetCountriesJson"  },  {    "type": "delete",    "url": "/api/sessions",    "title": "Sign out",    "group": "Sessions",    "success": {      "fields": {        "200": [          {            "group": "200",            "type": "void",            "optional": false,            "field": "void",            "description": "<p>void</p>"          }        ]      }    },    "version": "0.0.0",    "filename": "routes/sessions.js",    "groupTitle": "Sessions",    "name": "DeleteApiSessions"  },  {    "type": "post",    "url": "/api/sessions",    "title": "Sign in",    "group": "Sessions",    "parameter": {      "fields": {        "Parameter": [          {            "group": "Parameter",            "type": "string",            "optional": false,            "field": "id",            "description": "<p>User ID, can be id, username, mobilephone, email</p>"          },          {            "group": "Parameter",            "type": "string",            "optional": false,            "field": "password",            "description": "<p>User password</p>"          }        ]      },      "examples": [        {          "title": "Request-example:",          "content": "{\n  \"id\": \"12345678901\",\n  \"password\": \"000000\" \n}",          "type": "json"        }      ]    },    "success": {      "fields": {        "200": [          {            "group": "200",            "type": "object",            "optional": false,            "field": "void",            "description": "<p>User Object</p>"          }        ],        "204": [          {            "group": "204",            "type": "void",            "optional": false,            "field": "void",            "description": "<p>No returned object when no params are passed</p>"          }        ],        "403": [          {            "group": "403",            "type": "void",            "optional": false,            "field": "void",            "description": "<p>No Access denied</p>"          }        ]      }    },    "version": "0.0.0",    "filename": "routes/sessions.js",    "groupTitle": "Sessions",    "name": "PostApiSessions"  },  {    "type": "delete",    "url": "/api/users/:id",    "title": "Delete a user",    "group": "Users",    "success": {      "fields": {        "200": [          {            "group": "200",            "type": "void",            "optional": false,            "field": "void",            "description": "<p>void</p>"          }        ]      }    },    "version": "0.0.0",    "filename": "routes/users.js",    "groupTitle": "Users",    "name": "DeleteApiUsersId"  },  {    "type": "get",    "url": "/api/users",    "title": "Get all users",    "group": "Users",    "parameter": {      "fields": {        "Query String": [          {            "group": "Query String",            "type": "string",            "optional": true,            "field": "id",            "description": "<p>User ID</p>"          },          {            "group": "Query String",            "type": "string",            "optional": true,            "field": "mobilephone",            "description": "<p>User mobilephone</p>"          },          {            "group": "Query String",            "type": "string",            "allowedValues": [              "'teacher'",              "'student'",              "'admin'"            ],            "optional": true,            "field": "role_id",            "defaultValue": "teacher,student",            "description": "<p>User's role</p>"          },          {            "group": "Query String",            "type": "boolean",            "allowedValues": [              "0",              "1"            ],            "optional": true,            "field": "gender",            "defaultValue": "0,1",            "description": "<p>User gender</p>"          },          {            "group": "Query String",            "type": "string",            "allowedValues": [              "'online'",              "'offline'",              "'both'"            ],            "optional": true,            "field": "place",            "defaultValue": "both",            "description": "<p>Where do the users want to have the class</p>"          },          {            "group": "Query String",            "type": "string",            "optional": true,            "field": "city",            "description": "<p>The city a user is currently living in, check cities list</p>"          },          {            "group": "Query String",            "type": "string",            "optional": true,            "field": "province",            "description": "<p>The province a user is currently living in, check provinces list</p>"          },          {            "group": "Query String",            "type": "string",            "optional": true,            "field": "countries",            "description": "<p>The countries a user is currently living in, check countries list</p>"          },          {            "group": "Query String",            "type": "boolean",            "optional": true,            "field": "active",            "defaultValue": "0,1",            "description": "<p>Is a user wished to be found</p>"          },          {            "group": "Query String",            "type": "boolean",            "optional": true,            "field": "available",            "defaultValue": "0,1",            "description": "<p>Is a user opened for booking</p>"          },          {            "group": "Query String",            "type": "integer",            "optional": true,            "field": "page",            "defaultValue": "1",            "description": "<p>Pagination</p>"          }        ]      },      "examples": [        {          "title": "Request-example:",          "content": "/api/users?id=1&gender=1,0&place=online&role_id=teacher&city=4503,1101",          "type": "json"        }      ]    },    "success": {      "fields": {        "200": [          {            "group": "200",            "type": "object[]",            "optional": false,            "field": "void",            "description": "<p>Array contains all users object</p>"          }        ]      }    },    "version": "0.0.0",    "filename": "routes/users.js",    "groupTitle": "Users",    "name": "GetApiUsers"  },  {    "type": "get",    "url": "/api/users/:id",    "title": "Get a user",    "group": "Users",    "success": {      "fields": {        "200": [          {            "group": "200",            "type": "object",            "optional": false,            "field": "void",            "description": "<p>User object</p>"          }        ]      }    },    "version": "0.0.0",    "filename": "routes/users.js",    "groupTitle": "Users",    "name": "GetApiUsersId"  },  {    "type": "get",    "url": "/api/users/:id/followers",    "title": "Get a user's followers",    "group": "Users",    "parameter": {      "fields": {        "Query String": [          {            "group": "Query String",            "type": "integer",            "optional": true,            "field": "page",            "defaultValue": "1",            "description": "<p>Pagination</p>"          }        ]      }    },    "success": {      "fields": {        "200": [          {            "group": "200",            "type": "object[]",            "optional": false,            "field": "void",            "description": "<p>Array containing a user's followers</p>"          }        ]      }    },    "version": "0.0.0",    "filename": "routes/users.js",    "groupTitle": "Users",    "name": "GetApiUsersIdFollowers"  },  {    "type": "get",    "url": "/api/users/:id/followings",    "title": "Get a user's followings",    "group": "Users",    "parameter": {      "fields": {        "Query String": [          {            "group": "Query String",            "type": "integer",            "optional": true,            "field": "page",            "defaultValue": "1",            "description": "<p>Pagination</p>"          }        ]      }    },    "success": {      "fields": {        "200": [          {            "group": "200",            "type": "object[]",            "optional": false,            "field": "void",            "description": "<p>Array containing a user's followings</p>"          }        ]      }    },    "version": "0.0.0",    "filename": "routes/users.js",    "groupTitle": "Users",    "name": "GetApiUsersIdFollowings"  },  {    "type": "get",    "url": "/api/users/:id/students",    "title": "Get a user's students",    "group": "Users",    "parameter": {      "fields": {        "Query String": [          {            "group": "Query String",            "type": "integer",            "optional": true,            "field": "page",            "defaultValue": "1",            "description": "<p>Pagination</p>"          }        ]      }    },    "success": {      "fields": {        "200": [          {            "group": "200",            "type": "object[]",            "optional": false,            "field": "void",            "description": "<p>Array containing a user's students</p>"          }        ]      }    },    "version": "0.0.0",    "filename": "routes/users.js",    "groupTitle": "Users",    "name": "GetApiUsersIdStudents"  },  {    "type": "get",    "url": "/api/users/:id/teachers",    "title": "Get a user's teachers",    "group": "Users",    "parameter": {      "fields": {        "Query String": [          {            "group": "Query String",            "type": "integer",            "optional": true,            "field": "page",            "defaultValue": "1",            "description": "<p>Pagination</p>"          }        ]      }    },    "success": {      "fields": {        "200": [          {            "group": "200",            "type": "object[]",            "optional": false,            "field": "void",            "description": "<p>Array containing a user's teachers</p>"          }        ]      }    },    "version": "0.0.0",    "filename": "routes/users.js",    "groupTitle": "Users",    "name": "GetApiUsersIdTeachers"  },  {    "type": "post",    "url": "/api/users/:id",    "title": "Update a user",    "group": "Users",    "success": {      "fields": {        "200": [          {            "group": "200",            "type": "object",            "optional": false,            "field": "void",            "description": "<p>The updated user object</p>"          }        ]      }    },    "version": "0.0.0",    "filename": "routes/users.js",    "groupTitle": "Users",    "name": "PostApiUsersId"  },  {    "type": "put",    "url": "/api/users",    "title": "Create a new user",    "group": "Users",    "parameter": {      "fields": {        "Parameter": [          {            "group": "Parameter",            "type": "string",            "optional": false,            "field": "name",            "description": "<p>User name</p>"          },          {            "group": "Parameter",            "type": "string",            "optional": false,            "field": "mobilephone",            "description": "<p>User mobilephone number</p>"          },          {            "group": "Parameter",            "type": "string",            "optional": false,            "field": "password",            "description": "<p>User passowrd</p>"          }        ]      },      "examples": [        {          "title": "Request-example:",          "content": "{\n  \"name\": \"Tony\",\n  \"mobilephone\": \"12345678901\",\n  \"password\": \"000000\" \n}",          "type": "json"        }      ]    },    "success": {      "fields": {        "201": [          {            "group": "201",            "type": "object",            "optional": false,            "field": "void",            "description": "<p>The newly created user object</p>"          }        ]      }    },    "version": "0.0.0",    "filename": "routes/users.js",    "groupTitle": "Users",    "name": "PutApiUsers"  }]
